LICENSE.txt
README.md
setup.cfg
setup.py
aritmetica/__init__.py
aritmetica/operacoes.py
aritmetica.egg-info/PKG-INFO
aritmetica.egg-info/SOURCES.txt
aritmetica.egg-info/dependency_links.txt
aritmetica.egg-info/top_level.txt