Metadata-Version: 1.0
Name: aritmetica
Version: 0.1
Summary: Pacote python para operações aritméticas
Home-page: https://github.com/marcos-de-sousa
Author: Marcos Paulo Alves de Sousa
Author-email: msousa@museu-goeldi.br
License: MIT License
Platform: UNKNOWN
